ssb_timeseries/__init__.py
ssb_timeseries/__main__.py
ssb_timeseries/catalog.py
ssb_timeseries/config.py
ssb_timeseries/dataframes.py
ssb_timeseries/dataset.py
ssb_timeseries/dates.py
ssb_timeseries/intervals.py
ssb_timeseries/io/__init__.py
ssb_timeseries/io/fs.py
ssb_timeseries/io/json_helpers.py
ssb_timeseries/io/json_metadata.py
ssb_timeseries/io/parquet_schema.py
ssb_timeseries/io/protocols.py
ssb_timeseries/io/pyarrow_hive.py
ssb_timeseries/io/pyarrow_simple.py
ssb_timeseries/io/snapshot.py
ssb_timeseries/logging.py
ssb_timeseries/meta/__init__.py
ssb_timeseries/meta/formatters.py
ssb_timeseries/meta/loaders.py
ssb_timeseries/meta/tags.py
ssb_timeseries/meta/taxonomy.py
ssb_timeseries/py.typed
ssb_timeseries/sample_data.py
ssb_timeseries/sample_metadata.py
ssb_timeseries/types.py
ssb_timeseries-0.7.4.dist-info/METADATA
ssb_timeseries-0.7.4.dist-info/WHEEL
ssb_timeseries-0.7.4.dist-info/entry_points.txt
ssb_timeseries-0.7.4.dist-info/licenses/LICENSE
ssb_timeseries-0.7.4.dist-info/RECORD
