Metadata-Version: 2.4
Name: ssb-timeseries
Version: 0.7.4
Summary: SSB Timeseries
License-Expression: MIT
License-File: LICENSE
Author: Bernhard Ryeng
Author-email: bernhard.ryeng@ssb.no
Requires-Python: >=3.11, <4.0, !=3.14.1
Classifier: Development Status :: 4 - Beta
Classifier: Programming Language :: Python :: 3
Classifier: Programming Language :: Python :: 3.11
Classifier: Programming Language :: Python :: 3.12
Classifier: Programming Language :: Python :: 3.13
Classifier: Programming Language :: Python :: 3.14
Requires-Dist: bigtree (>=0.17.2)
Requires-Dist: click (>=8.1.7)
Requires-Dist: duckdb (>=1.0.0)
Requires-Dist: gcsfs (>=2025.12.0,<2026.0.0)
Requires-Dist: matplotlib (>=3.8.4)
Requires-Dist: multipledispatch (>=1.0.0)
Requires-Dist: narwhals (>=1.38.0)
Requires-Dist: networkx (>=3.6.1,<4.0.0)
Requires-Dist: networkx-stubs (>=0.0.1,<0.0.2)
Requires-Dist: numpy (>=1.26.4)
Requires-Dist: pandas (>=2.1.1)
Requires-Dist: polars (>=1.5.0)
Requires-Dist: pyarrow (>=14.0.0)
Requires-Dist: python-dateutil (>=2.9.0.post0)
Requires-Dist: ssb-klass-python (>=0.0.7)
Requires-Dist: tomli (>=2.1.0)
Requires-Dist: tomli-w (>=1.1.0)
Requires-Dist: typing-extensions (>=4.11.0)
Requires-Dist: tzdata (>=2025.2)
Project-URL: Changelog, https://github.com/statisticsnorway/ssb-timeseries/releases
Project-URL: Documentation, https://statisticsnorway.github.io/ssb-timeseries
Project-URL: Homepage, https://github.com/statisticsnorway/ssb-timeseries
Project-URL: Repository, https://github.com/statisticsnorway/ssb-timeseries
